mapcat/__init__.py
mapcat/alembic.ini
mapcat/helper.py
mapcat/alembic/env.py
mapcat/alembic/script.py.mako
mapcat/alembic/versions/1195d17201ba_add_notes_missing_field_to_atomic_maps.py
mapcat/alembic/versions/57b97937e1bc_.py
mapcat/alembic/versions/6ce7e94dfd2d_add_filtered_masps.py
mapcat/alembic/versions/78293df04081_create_depth_1_map_table.py
mapcat/alembic/versions/976527c198bd_add_indices.py
mapcat/alembic/versions/bc2be980cfe7_add_notes_json_field_to_depth_one_maps.py
mapcat/alembic/versions/fd6670a1fdbe_update_atomic_map_coadd_table.py
mapcat/client/__init__.py
mapcat/client/core.py
mapcat/database/__init__.py
mapcat/database/atomic_coadd.py
mapcat/database/atomic_map.py
mapcat/database/depth_one_coadd.py
mapcat/database/depth_one_map.py
mapcat/database/links.py
mapcat/database/pipeline_information.py
mapcat/database/pointing_residual.py
mapcat/database/sky_coverage.py
mapcat/database/time_domain_processing.py
mapcat/database/tod.py
mapcat/toolkit/__init__.py
mapcat/toolkit/act.py
mapcat/toolkit/mapmaking.py
mapcat-0.1.0.dist-info/METADATA
mapcat-0.1.0.dist-info/WHEEL
mapcat-0.1.0.dist-info/entry_points.txt
mapcat-0.1.0.dist-info/top_level.txt
mapcat-0.1.0.dist-info/RECORD
