Metadata-Version: 2.4
Name: mapcat
Version: 0.1.0
Requires-Python: >=3.11
Requires-Dist: sqlmodel
Requires-Dist: sqlalchemy[asyncio]
Requires-Dist: aiosqlite
Requires-Dist: alembic
Requires-Dist: pydantic_settings
Provides-Extra: dev
Requires-Dist: pytest; extra == "dev"
Requires-Dist: ruff; extra == "dev"
Requires-Dist: testcontainers; extra == "dev"
Requires-Dist: coverage; extra == "dev"
Requires-Dist: pytest-cov; extra == "dev"
Requires-Dist: pytest-asyncio; extra == "dev"
Requires-Dist: pre-commit; extra == "dev"
Requires-Dist: gevent; extra == "dev"
